RPiLCD/I2CRasp.py
RPiLCD/LDCRasp.py
RPiLCD/__init__.py
lcdrpi-1.0.0.dist-info/LICENSE
lcdrpi-1.0.0.dist-info/METADATA
lcdrpi-1.0.0.dist-info/WHEEL
lcdrpi-1.0.0.dist-info/entry_points.txt
lcdrpi-1.0.0.dist-info/RECORD
