Metadata-Version: 2.3
Name: LCDRPi
Version: 1.0.0
Summary: Esta librería es para el manejo de pantallas LCD en la Raspberry Pi
License: LGPL
Keywords: raspberrypi,lcd,i2c,display
Author: Esteban, herrerazanecheverry@gmail.com
Requires-Python: >=3.9,<3.12
Classifier: License :: Other/Proprietary License
Classifier: Programming Language :: Python :: 3
Classifier: Programming Language :: Python :: 3.9
Classifier: Programming Language :: Python :: 3.10
Classifier: Programming Language :: Python :: 3.11
Requires-Dist: rpi-gpio (>=0.7.1,<0.8.0)
Requires-Dist: smbus (>=1.1.post2,<2.0)
